README.md
setup.py
FBRank/__init__.py
FBRank/main.py
FBRank.egg-info/PKG-INFO
FBRank.egg-info/SOURCES.txt
FBRank.egg-info/dependency_links.txt
FBRank.egg-info/entry_points.txt
FBRank.egg-info/requires.txt
FBRank.egg-info/top_level.txt
FBRank/object/Club.py
FBRank/object/League.py
FBRank/object/Player.py
FBRank/object/__init__.py
FBRank/parse/League.py
FBRank/parse/__init__.py
FBRank/utils/__init__.py
FBRank/utils/exceptions.py
FBRank/utils/utils.py