Metadata-Version: 1.1
Name: FBRank
Version: 1.8.0
Summary: A commandline tool helps you visualize league rank and other imformation
Home-page: https://github.com/Allianzcortex/FBRank
Author: Allianzcortex
Author-email: iamwanghz@gmail.com
License: MIT
Keywords: Football Manager SetupTools
Platform: UNKNOWN
Classifier: Development Status :: 3 - Alpha
Classifier: License :: OSI Approved :: MIT License
Classifier: Programming Language :: Python :: 3.5
